{
  "ticker": "QBTS",
  "updated_at": "2026-06-29T05:26:25.033455",
  "stats": {},
  "superinvestors": [],
  "activity": {},
  "insiders": {
    "summary": {
      "buys": {
        "count": 1,
        "amount": 1795
      },
      "sells": {
        "count": 53,
        "amount": 120768059
      }
    },
    "transactions": [
      {
        "filing_date": "16 Jun 2026 17:34",
        "reporter": "GHAI ROHIT",
        "relationship": "Director",
        "transaction_date": "15 Jun 2026",
        "transaction_type": "Sale",
        "shares": 13518,
        "price": 26.4133,
        "value": 357055
      },
      {
        "filing_date": "16 Jun 2026 17:15",
        "reporter": "MARKOVICH JOHN M.",
        "relationship": "Chief Financial Officer",
        "transaction_date": "12 Jun 2026",
        "transaction_type": "Sale",
        "shares": 46043,
        "price": 24.01,
        "value": 1105492
      },
      {
        "filing_date": "16 Jun 2026 17:15",
        "reporter": "MARKOVICH JOHN M.",
        "relationship": "Chief Financial Officer",
        "transaction_date": "15 Jun 2026",
        "transaction_type": "Sale",
        "shares": 100000,
        "price": 25.75,
        "value": 2575000
      },
      {
        "filing_date": "16 Jun 2026 17:15",
        "reporter": "MARKOVICH JOHN M.",
        "relationship": "Chief Financial Officer",
        "transaction_date": "15 Jun 2026",
        "transaction_type": "Sale",
        "shares": 100000,
        "price": 25.68,
        "value": 2568000
      },
      {
        "filing_date": "10 Jun 2026 16:07",
        "reporter": "BARATZ ALAN E",
        "relationship": "President & CEO",
        "transaction_date": "08 Jun 2026",
        "transaction_type": "Sale",
        "shares": 687627,
        "price": 26.13,
        "value": 17967694
      },
      {
        "filing_date": "10 Jun 2026 16:07",
        "reporter": "MARKOVICH JOHN M.",
        "relationship": "Chief Financial Officer",
        "transaction_date": "08 Jun 2026",
        "transaction_type": "Sale",
        "shares": 50979,
        "price": 26.24,
        "value": 1337689
      },
      {
        "filing_date": "10 Jun 2026 16:07",
        "reporter": "MARKOVICH JOHN M.",
        "relationship": "Chief Financial Officer",
        "transaction_date": "09 Jun 2026",
        "transaction_type": "Sale",
        "shares": 70,
        "price": 26.54,
        "value": 1858
      },
      {
        "filing_date": "08 Jun 2026 16:14",
        "reporter": "DILULLO JOHN D",
        "relationship": "Director",
        "transaction_date": "05 Jun 2026",
        "transaction_type": "Sale",
        "shares": 7850,
        "price": 24.4343,
        "value": 191809
      },
      {
        "filing_date": "04 Jun 2026 17:20",
        "reporter": "MARKOVICH JOHN M.",
        "relationship": "Chief Financial Officer",
        "transaction_date": "02 Jun 2026",
        "transaction_type": "Sale",
        "shares": 2908,
        "price": 31.0,
        "value": 90148
      },
      {
        "filing_date": "27 May 2026 17:31",
        "reporter": "MARKOVICH JOHN M.",
        "relationship": "Chief Financial Officer",
        "transaction_date": "22 May 2026",
        "transaction_type": "Sale",
        "shares": 328752,
        "price": 27.7037,
        "value": 9107647
      },
      {
        "filing_date": "22 May 2026 16:38",
        "reporter": "NGUYEN DIANE",
        "relationship": "EVP, Chief Legal Officer & GC",
        "transaction_date": "21 May 2026",
        "transaction_type": "Sale",
        "shares": 40000,
        "price": 25.014,
        "value": 1000560
      },
      {
        "filing_date": "21 May 2026 17:15",
        "reporter": "AMES SOPHIE C",
        "relationship": "Exec. Vice President & CHRO",
        "transaction_date": "20 May 2026",
        "transaction_type": "Sale",
        "shares": 23025,
        "price": 18.9765,
        "value": 436934
      },
      {
        "filing_date": "21 Apr 2026 17:19",
        "reporter": "AMES SOPHIE C",
        "relationship": "Exec. Vice President & CHRO",
        "transaction_date": "20 Apr 2026",
        "transaction_type": "Sale",
        "shares": 3070,
        "price": 21.3513,
        "value": 65548
      },
      {
        "filing_date": "17 Mar 2026 17:34",
        "reporter": "GHAI ROHIT",
        "relationship": "Director",
        "transaction_date": "16 Mar 2026",
        "transaction_type": "Sale",
        "shares": 10000,
        "price": 17.6168,
        "value": 176168
      },
      {
        "filing_date": "17 Mar 2026 17:28",
        "reporter": "NGUYEN DIANE",
        "relationship": "EVP, Chief Legal Officer & GC",
        "transaction_date": "13 Mar 2026",
        "transaction_type": "Sale",
        "shares": 2532,
        "price": 17.6278,
        "value": 44634
      },
      {
        "filing_date": "17 Mar 2026 17:27",
        "reporter": "MARKOVICH JOHN M.",
        "relationship": "Chief Financial Officer",
        "transaction_date": "13 Mar 2026",
        "transaction_type": "Sale",
        "shares": 10706,
        "price": 17.6278,
        "value": 188723
      },
      {
        "filing_date": "06 Mar 2026 16:30",
        "reporter": "DILULLO JOHN D",
        "relationship": "Director",
        "transaction_date": "05 Mar 2026",
        "transaction_type": "Sale",
        "shares": 8000,
        "price": 18.0122,
        "value": 144098
      },
      {
        "filing_date": "17 Feb 2026 17:11",
        "reporter": "NGUYEN DIANE",
        "relationship": "EVP, Chief Legal Officer & GC",
        "transaction_date": "13 Feb 2026",
        "transaction_type": "Sale",
        "shares": 1451,
        "price": 19.7597,
        "value": 28671
      },
      {
        "filing_date": "15 Jan 2026 17:12",
        "reporter": "NGUYEN DIANE",
        "relationship": "EVP, Chief Legal Officer & GC",
        "transaction_date": "13 Jan 2026",
        "transaction_type": "Sale",
        "shares": 20000,
        "price": 28.8579,
        "value": 577158
      },
      {
        "filing_date": "15 Jan 2026 17:12",
        "reporter": "NGUYEN DIANE",
        "relationship": "EVP, Chief Legal Officer & GC",
        "transaction_date": "14 Jan 2026",
        "transaction_type": "Sale",
        "shares": 4519,
        "price": 28.0623,
        "value": 126814
      },
      {
        "filing_date": "15 Jan 2026 17:09",
        "reporter": "MARKOVICH JOHN M.",
        "relationship": "Chief Financial Officer",
        "transaction_date": "14 Jan 2026",
        "transaction_type": "Sale",
        "shares": 9179,
        "price": 28.0623,
        "value": 257584
      },
      {
        "filing_date": "15 Jan 2026 17:07",
        "reporter": "BARATZ ALAN E",
        "relationship": "President & CEO",
        "transaction_date": "14 Jan 2026",
        "transaction_type": "Sale",
        "shares": 35013,
        "price": 28.0623,
        "value": 982545
      },
      {
        "filing_date": "23 Dec 2025 16:16",
        "reporter": "BARATZ ALAN E",
        "relationship": "President & CEO",
        "transaction_date": "22 Dec 2025",
        "transaction_type": "Sale",
        "shares": 793712,
        "price": 30.1282,
        "value": 23913114
      },
      {
        "filing_date": "23 Dec 2025 16:16",
        "reporter": "MARKOVICH JOHN M.",
        "relationship": "Chief Financial Officer",
        "transaction_date": "22 Dec 2025",
        "transaction_type": "Sale",
        "shares": 100000,
        "price": 30.0262,
        "value": 3002620
      },
      {
        "filing_date": "16 Dec 2025 17:06",
        "reporter": "GHAI ROHIT",
        "relationship": "Director",
        "transaction_date": "15 Dec 2025",
        "transaction_type": "Sale",
        "shares": 10000,
        "price": 24.2841,
        "value": 242841
      },
      {
        "filing_date": "16 Dec 2025 16:59",
        "reporter": "NGUYEN DIANE",
        "relationship": "EVP, Chief Legal Officer & GC",
        "transaction_date": "15 Dec 2025",
        "transaction_type": "Sale",
        "shares": 2733,
        "price": 23.8944,
        "value": 65303
      },
      {
        "filing_date": "16 Dec 2025 16:57",
        "reporter": "MARKOVICH JOHN M.",
        "relationship": "Chief Financial Officer",
        "transaction_date": "15 Dec 2025",
        "transaction_type": "Sale",
        "shares": 11562,
        "price": 23.8944,
        "value": 276267
      },
      {
        "filing_date": "08 Dec 2025 17:36",
        "reporter": "DILULLO JOHN D",
        "relationship": "Director",
        "transaction_date": "05 Dec 2025",
        "transaction_type": "Sale",
        "shares": 8000,
        "price": 27.3612,
        "value": 218890
      },
      {
        "filing_date": "05 Dec 2025 19:21",
        "reporter": "NIELSEN KIRSTJEN",
        "relationship": "Director",
        "transaction_date": "03 Dec 2025",
        "transaction_type": "Sale",
        "shares": 7000,
        "price": 22.62,
        "value": 158340
      },
      {
        "filing_date": "05 Dec 2025 19:21",
        "reporter": "MARKOVICH JOHN M.",
        "relationship": "Chief Financial Officer",
        "transaction_date": "03 Dec 2025",
        "transaction_type": "Sale",
        "shares": 100000,
        "price": 25.05,
        "value": 2505000
      },
      {
        "filing_date": "05 Dec 2025 19:21",
        "reporter": "MARKOVICH JOHN M.",
        "relationship": "Chief Financial Officer",
        "transaction_date": "04 Dec 2025",
        "transaction_type": "Sale",
        "shares": 100000,
        "price": 27.56,
        "value": 2756000
      },
      {
        "filing_date": "21 Nov 2025 17:14",
        "reporter": "MARKOVICH JOHN M.",
        "relationship": "Chief Financial Officer",
        "transaction_date": "20 Nov 2025",
        "transaction_type": "Sale",
        "shares": 200000,
        "price": 22.94,
        "value": 4588000
      },
      {
        "filing_date": "18 Nov 2025 19:01",
        "reporter": "WEST STEVEN M",
        "relationship": "Director",
        "transaction_date": "18 Nov 2025",
        "transaction_type": "Purchase",
        "shares": 82,
        "price": 21.89,
        "value": 1795
      },
      {
        "filing_date": "14 Nov 2025 17:01",
        "reporter": "NGUYEN DIANE",
        "relationship": "EVP, Chief Legal Officer & GC",
        "transaction_date": "13 Nov 2025",
        "transaction_type": "Sale",
        "shares": 20000,
        "price": 23.6641,
        "value": 473282
      },
      {
        "filing_date": "14 Nov 2025 17:01",
        "reporter": "NGUYEN DIANE",
        "relationship": "EVP, Chief Legal Officer & GC",
        "transaction_date": "13 Nov 2025",
        "transaction_type": "Sale",
        "shares": 2803,
        "price": 23.1744,
        "value": 64958
      },
      {
        "filing_date": "14 Nov 2025 17:01",
        "reporter": "BARATZ ALAN E",
        "relationship": "President & CEO",
        "transaction_date": "13 Nov 2025",
        "transaction_type": "Sale",
        "shares": 168102,
        "price": 23.1744,
        "value": 3895663
      },
      {
        "filing_date": "14 Nov 2025 17:00",
        "reporter": "MARKOVICH JOHN M.",
        "relationship": "Chief Financial Officer",
        "transaction_date": "13 Nov 2025",
        "transaction_type": "Sale",
        "shares": 98060,
        "price": 23.1744,
        "value": 2272482
      },
      {
        "filing_date": "13 Nov 2025 17:37",
        "reporter": "BARATZ ALAN E",
        "relationship": "President & CEO",
        "transaction_date": "11 Nov 2025",
        "transaction_type": "Sale",
        "shares": 806288,
        "price": 28.8686,
        "value": 23276406
      },
      {
        "filing_date": "15 Oct 2025 17:05",
        "reporter": "NGUYEN DIANE",
        "relationship": "EVP, Chief Legal Officer & GC",
        "transaction_date": "14 Oct 2025",
        "transaction_type": "Sale",
        "shares": 20827,
        "price": 43.7434,
        "value": 911044
      },
      {
        "filing_date": "15 Oct 2025 17:03",
        "reporter": "MARKOVICH JOHN M.",
        "relationship": "Chief Financial Officer",
        "transaction_date": "14 Oct 2025",
        "transaction_type": "Sale",
        "shares": 7994,
        "price": 43.7434,
        "value": 349685
      },
      {
        "filing_date": "15 Oct 2025 17:02",
        "reporter": "BARATZ ALAN E",
        "relationship": "President & CEO",
        "transaction_date": "14 Oct 2025",
        "transaction_type": "Sale",
        "shares": 31369,
        "price": 43.7434,
        "value": 1372187
      },
      {
        "filing_date": "17 Sep 2025 16:35",
        "reporter": "GHAI ROHIT",
        "relationship": "Director",
        "transaction_date": "15 Sep 2025",
        "transaction_type": "Sale",
        "shares": 10000,
        "price": 17.932,
        "value": 179320
      },
      {
        "filing_date": "17 Sep 2025 16:34",
        "reporter": "DILULLO JOHN D",
        "relationship": "Director",
        "transaction_date": "15 Sep 2025",
        "transaction_type": "Sale",
        "shares": 8000,
        "price": 17.929,
        "value": 143432
      },
      {
        "filing_date": "12 Sep 2025 17:29",
        "reporter": "MARKOVICH JOHN M.",
        "relationship": "Chief Financial Officer",
        "transaction_date": "12 Sep 2025",
        "transaction_type": "Sale",
        "shares": 50000,
        "price": 17.5,
        "value": 875000
      },
      {
        "filing_date": "12 Sep 2025 17:29",
        "reporter": "MARKOVICH JOHN M.",
        "relationship": "Chief Financial Officer",
        "transaction_date": "10 Sep 2025",
        "transaction_type": "Sale",
        "shares": 50000,
        "price": 16.3,
        "value": 815000
      },
      {
        "filing_date": "12 Sep 2025 17:29",
        "reporter": "MARKOVICH JOHN M.",
        "relationship": "Chief Financial Officer",
        "transaction_date": "11 Sep 2025",
        "transaction_type": "Sale",
        "shares": 50000,
        "price": 16.3,
        "value": 815000
      },
      {
        "filing_date": "20 Aug 2025 16:30",
        "reporter": "WEST STEVEN M",
        "relationship": "Director",
        "transaction_date": "13 Aug 2025",
        "transaction_type": "Sale A",
        "shares": 119000,
        "price": 18.06,
        "value": 2149140
      },
      {
        "filing_date": "20 Aug 2025 16:30",
        "reporter": "WEST STEVEN M",
        "relationship": "Director",
        "transaction_date": "13 Aug 2025",
        "transaction_type": "Sale A",
        "shares": 25000,
        "price": 18.176,
        "value": 454400
      },
      {
        "filing_date": "15 Aug 2025 17:10",
        "reporter": "WEST STEVEN M",
        "relationship": "Director",
        "transaction_date": "13 Aug 2025",
        "transaction_type": "Sale",
        "shares": 119000,
        "price": 18.06,
        "value": 2149140
      },
      {
        "filing_date": "15 Aug 2025 17:10",
        "reporter": "WEST STEVEN M",
        "relationship": "Director",
        "transaction_date": "13 Aug 2025",
        "transaction_type": "Sale",
        "shares": 25000,
        "price": 18.176,
        "value": 454400
      },
      {
        "filing_date": "14 Aug 2025 21:03",
        "reporter": "NGUYEN DIANE",
        "relationship": "EVP, Chief Legal Officer & GC",
        "transaction_date": "13 Aug 2025",
        "transaction_type": "Sale",
        "shares": 25634,
        "price": 18.113,
        "value": 464309
      },
      {
        "filing_date": "14 Aug 2025 21:03",
        "reporter": "NGUYEN DIANE",
        "relationship": "EVP, Chief Legal Officer & GC",
        "transaction_date": "13 Aug 2025",
        "transaction_type": "Sale",
        "shares": 39010,
        "price": 18.181,
        "value": 709241
      },
      {
        "filing_date": "14 Aug 2025 21:03",
        "reporter": "NGUYEN DIANE",
        "relationship": "EVP, Chief Legal Officer & GC",
        "transaction_date": "13 Aug 2025",
        "transaction_type": "Sale",
        "shares": 4626,
        "price": 18.54,
        "value": 85766
      },
      {
        "filing_date": "14 Aug 2025 21:02",
        "reporter": "MARKOVICH JOHN M.",
        "relationship": "Chief Financial Officer",
        "transaction_date": "12 Aug 2025",
        "transaction_type": "Sale",
        "shares": 100000,
        "price": 18.0,
        "value": 1800000
      }
    ]
  }
}